setup.py
pycannon/__init__.py
pycannon/connection.py
pycannon/django.py
pycannon.egg-info/PKG-INFO
pycannon.egg-info/SOURCES.txt
pycannon.egg-info/dependency_links.txt
pycannon.egg-info/requires.txt
pycannon.egg-info/top_level.txt